context_aware_chunker/__init__.py
context_aware_chunker/chunking_models.py
context_aware_chunker/text_splitter.py
context_aware_chunker-0.0.2.dist-info/LICENSE
context_aware_chunker-0.0.2.dist-info/METADATA
context_aware_chunker-0.0.2.dist-info/WHEEL
context_aware_chunker-0.0.2.dist-info/top_level.txt
context_aware_chunker-0.0.2.dist-info/RECORD
