Metadata-Version: 2.1
Name: context-aware-chunker
Version: 0.0.2
Summary: Context aware chunking using perplexity
Home-page: https://github.com/wordlabs-io/context_aware_chunker
Author: Tanishk Kithannae
Author-email: tanishk.kithannae@wordlabs.io
Keywords: python,rag
Classifier: Development Status :: 3 - Alpha
Classifier: Intended Audience :: Developers
Classifier: Programming Language :: Python :: 3
Classifier: Operating System :: MacOS :: MacOS X
Classifier: Operating System :: Microsoft :: Windows
License-File: LICENSE
Requires-Dist: transformers
Requires-Dist: pysbd
